[
  {
    "symbol": "FND79.NZ",
    "date": "2022-01-18",
    "price": 1.6585000000000000852
  },
  {
    "symbol": "FND79.NZ",
    "date": "2022-01-19",
    "price": 1.6519999999999999129
  },
  {
    "symbol": "FND79.NZ",
    "date": "2022-01-20",
    "price": 1.6533999999999999808
  },
  {
    "symbol": "FND79.NZ",
    "date": "2022-01-21",
    "price": 1.6585000000000000852
  },
  {
    "symbol": "FND79.NZ",
    "date": "2022-01-24",
    "price": 1.6588000000000000522
  },
  {
    "symbol": "FND79.NZ",
    "date": "2022-01-25",
    "price": 1.6554999999999999715
  },
  {
    "symbol": "FND79.NZ",
    "date": "2022-01-26",
    "price": 1.6525000000000000799
  },
  {
    "symbol": "FND79.NZ",
    "date": "2022-01-27",
    "price": 1.6487000000000000543
  },
  {
    "symbol": "FND79.NZ",
    "date": "2022-01-28",
    "price": 1.6524000000000000909
  },
  { "symbol": "FND79.NZ", "date": "2022-01-31", "price": 1.6527000000000000579 }
]
