[
  {
    "symbol": "FND20410.NZ",
    "date": "2022-05-23",
    "price": 1.0517000000000000792
  },
  {
    "symbol": "VAN1579.AU",
    "date": "2022-05-27",
    "price": 1.4835000000000000408
  },
  {
    "symbol": "FND1423.NZ",
    "date": "2022-05-30",
    "price": 1.9150000000000000355
  },
  {
    "symbol": "FND79.NZ",
    "date": "2022-05-30",
    "price": 1.5707899999999999085
  },
  {
    "symbol": "FND8205.NZ",
    "date": "2022-05-30",
    "price": 1.2070600000000000218
  },
  {
    "symbol": "FND8207.NZ",
    "date": "2022-05-30",
    "price": 1.3089999999999999413
  },
  { "symbol": "FUEMAV30.VN", "date": "2022-05-31", "price": 15690.0 }
]
