[
  {
    "symbol": "FND20410.NZ",
    "date": "2023-06-22",
    "price": 1.1338999999999999079
  },
  {
    "symbol": "FND40819.NZ",
    "date": "2023-06-23",
    "price": 1.1073999999999999399
  },
  {
    "symbol": "VAN1579.AU",
    "date": "2023-06-23",
    "price": 1.6029779154591787815
  },
  {
    "symbol": "FND1423.NZ",
    "date": "2023-06-23",
    "price": 1.9159999999999999253
  },
  {
    "symbol": "FUEMAV30.VN",
    "date": "2023-06-26",
    "price": 13329.999999999999999
  },
  {
    "symbol": "FUEMAV30.VN",
    "date": "2023-06-23",
    "price": 13359.999999999999999
  },
  {
    "symbol": "FUEMAV30.VN",
    "date": "2023-06-22",
    "price": 13219.999999999999999
  },
  { "symbol": "FUEMAV30.VN", "date": "2023-06-21", "price": 13150.0 },
  {
    "symbol": "FUEMAV30.VN",
    "date": "2023-06-20",
    "price": 13059.999999999999999
  }
]
