[
  {
    "symbol": "FND20410.NZ",
    "date": "2023-03-29",
    "price": 1.0744000000000000216
  },
  {
    "symbol": "FND40819.NZ",
    "date": "2023-03-30",
    "price": 1.0381000000000000227
  },
  {
    "symbol": "VAN1579.AU",
    "date": "2023-03-30",
    "price": 1.5251324073148797566
  },
  {
    "symbol": "FND1423.NZ",
    "date": "2023-03-30",
    "price": 1.9254000000000000003
  },
  {
    "symbol": "FUEMAV30.VN",
    "date": "2023-03-31",
    "price": 12689.999999999999999
  },
  { "symbol": "FUEMAV30.VN", "date": "2023-03-30", "price": 12620.0 },
  { "symbol": "FUEMAV30.VN", "date": "2023-03-29", "price": 12500.0 },
  { "symbol": "FUEMAV30.VN", "date": "2023-03-28", "price": 12500.0 },
  {
    "symbol": "FUEMAV30.VN",
    "date": "2023-03-27",
    "price": 12439.999999999999999
  }
]
