[
  {
    "symbol": "FND20410.NZ",
    "date": "2022-12-09",
    "price": 1.0599000000000000643
  },
  {
    "symbol": "VAN1579.AU",
    "date": "2022-12-13",
    "price": 1.4629000000000000891
  },
  {
    "symbol": "FND1423.NZ",
    "date": "2022-12-13",
    "price": 1.9305000000000001048
  },
  {
    "symbol": "FND79.NZ",
    "date": "2022-12-14",
    "price": 1.5370800000000000018
  },
  {
    "symbol": "FND8205.NZ",
    "date": "2022-12-14",
    "price": 1.2351600000000000356
  },
  {
    "symbol": "FND8207.NZ",
    "date": "2022-12-14",
    "price": 1.2597300000000000164
  },
  { "symbol": "FUEMAV30.VN", "date": "2022-12-14", "price": 12470.0 },
  {
    "symbol": "FUEMAV30.VN",
    "date": "2022-12-13",
    "price": 12439.999999999999999
  },
  { "symbol": "FUEMAV30.VN", "date": "2022-12-12", "price": 12240.0 },
  {
    "symbol": "FUEMAV30.VN",
    "date": "2022-12-09",
    "price": 12579.999999999999999
  },
  {
    "symbol": "FUEMAV30.VN",
    "date": "2022-12-08",
    "price": 12539.999999999999999
  }
]
